tuido-0.0.3.data/scripts/tuido
util/__init__.py
util/item.py
util/list_screen.py
util/screen.py
util/util.py
tuido-0.0.3.dist-info/LICENSE
tuido-0.0.3.dist-info/METADATA
tuido-0.0.3.dist-info/WHEEL
tuido-0.0.3.dist-info/top_level.txt
tuido-0.0.3.dist-info/RECORD
