Metadata-Version: 2.1
Name: tuido
Version: 0.0.3
Summary: TUI todo list
Home-page: https://github.com/bodneyc/tuido
Author: BenJC
Author-email: benjamin.carrington@gmail.com
License: UNKNOWN
Platform: UNKNOWN
Classifier: Programming Language :: Python :: 3
Classifier: License :: OSI Approved :: GNU General Public License v2 (GPLv2)
